{
    "AX": {
        "error": 0.0,
        "fit": "default",
        "references": [],
        "value": 1.0
    },
    "CDD": {
        "error": 0.002280603283261146,
        "fit": "Average",
        "reference_data": {
            "es": [
                0.0018105225596324055,
                0.0018907932779803358,
                0.0020132510219823354,
                0.0016906241302036458,
                0.0022299583131081243,
                0.0022699994730862806
            ],
            "vs": [
                1.1177227791879418,
                1.1211664128640004,
                1.1146908724960354,
                1.1194843714485947,
                1.1200398728539374,
                1.1194072333364016
            ],
            "xs": [
                1752110843.0,
                1752115091.0,
                1752125647.0,
                1752136247.0,
                1752146855.0,
                1752157469.0
            ]
        },
        "reference_detector": "H1",
        "references": [
            {
                "exclude": "ok",
                "record_id": "a-01-A-9808",
                "uuid": "5c04d3c4-2e79-4a58-9d30-29f48d0fd87a"
            },
            {
                "exclude": "ok",
                "record_id": "a-01-A-9809",
                "uuid": "f7cf6da9-36e2-437f-bc3d-752706c0b16f"
            },
            {
                "exclude": "ok",
                "record_id": "a-01-A-9810",
                "uuid": "b272c484-390e-48b5-a3f2-6fdb7a35a523"
            },
            {
                "exclude": "ok",
                "record_id": "a-01-A-9811",
                "uuid": "b8365f2e-348c-4e62-99a9-04b4818a65b3"
            },
            {
                "exclude": "ok",
                "record_id": "a-01-A-9812",
                "uuid": "d9e4e207-f47c-43b3-9cf7-68e8384f82ef"
            },
            {
                "exclude": "ok",
                "record_id": "a-01-A-9813",
                "uuid": "e0b1d4bd-28a8-4beb-bab3-736be6a7e76c"
            }
        ],
        "reviewed": true,
        "standard_ratio": 295.5,
        "value": 1.1187519236978185
    },
    "H1": {
        "error": 0.0,
        "fit": "default",
        "references": [],
        "value": 1.0
    },
    "L1": {
        "error": 0.0,
        "fit": "default",
        "references": [],
        "value": 1.0
    },
    "L2": {
        "error": 0.0,
        "fit": "default",
        "references": [],
        "value": 1.0
    }
}